inkript/__init__.py
inkript/enkrypt.py
inkript-0.0.4.dist-info/LICENSE.txt
inkript-0.0.4.dist-info/METADATA
inkript-0.0.4.dist-info/WHEEL
inkript-0.0.4.dist-info/top_level.txt
inkript-0.0.4.dist-info/RECORD
