Metadata-Version: 2.1
Name: inkript
Version: 0.0.4
Summary: to create keys to encrypt and decrypt files
Author: mose_tucker_0159
Author-email: mose.tucker.0159@gmail.com
Keywords: python
Classifier: Development Status :: 1 - Planning
Classifier: Intended Audience :: End Users/Desktop
Classifier: Programming Language :: Python :: 3
Classifier: Operating System :: Microsoft :: Windows
Classifier: Operating System :: MacOS
License-File: LICENSE.txt
Requires-Dist: cryptography
